topo/__init__.py
topo/base.py
topo/continuous.py
topo/discrete.py
topo/functional.py
topo/hints.py
topo-0.1.1.dist-info/LICENSE
topo-0.1.1.dist-info/METADATA
topo-0.1.1.dist-info/WHEEL
topo-0.1.1.dist-info/top_level.txt
topo-0.1.1.dist-info/RECORD
