Metadata-Version: 2.1
Name: topo
Version: 0.1.1
Summary: Topology models.
Home-page: https://github.com/lycantropos/topo/
Author: Azat Ibrakov
Author-email: azatibrakov@gmail.com
License: UNKNOWN
Download-URL: https://github.com/lycantropos/topo/archive/master.zip
Platform: UNKNOWN
Requires-Python: >=3.5
